{"trial_id": "0015", "hyperparameters": {"space": [{"class_name": "Int", "config": {"name": "num_layers", "default": null, "conditions": [], "min_value": 1, "max_value": 5, "step": 1, "sampling": "linear"}}, {"class_name": "Int", "config": {"name": "unit_0", "default": null, "conditions": [], "min_value": 32, "max_value": 160, "step": 32, "sampling": "linear"}}, {"class_name": "Choice", "config": {"name": "learning_rate", "default": 0.01, "conditions": [], "values": [0.01, 0.001, 0.0001], "ordered": true}}, {"class_name": "Int", "config": {"name": "unit_1", "default": null, "conditions": [], "min_value": 32, "max_value": 160, "step": 32, "sampling": "linear"}}, {"class_name": "Int", "config": {"name": "unit_2", "default": null, "conditions": [], "min_value": 32, "max_value": 160, "step": 32, "sampling": "linear"}}, {"class_name": "Int", "config": {"name": "unit_3", "default": null, "conditions": [], "min_value": 32, "max_value": 160, "step": 32, "sampling": "linear"}}, {"class_name": "Int", "config": {"name": "unit_4", "default": null, "conditions": [], "min_value": 32, "max_value": 160, "step": 32, "sampling": "linear"}}], "values": {"num_layers": 3, "unit_0": 96, "learning_rate": 0.001, "unit_1": 128, "unit_2": 128, "unit_3": 128, "unit_4": 32, "tuner/epochs": 2, "tuner/initial_epoch": 0, "tuner/bracket": 3, "tuner/round": 0}}, "metrics": {"metrics": {"accuracy": {"direction": "max", "observations": [{"value": [0.9682833552360535], "step": 1}]}, "loss": {"direction": "min", "observations": [{"value": [0.10327321290969849], "step": 1}]}, "val_accuracy": {"direction": "max", "observations": [{"value": [0.9666666388511658], "step": 1}]}, "val_loss": {"direction": "min", "observations": [{"value": [0.10951352119445801], "step": 1}]}}}, "score": 0.9666666388511658, "best_step": 1, "status": "COMPLETED", "message": null}